lookback/__init__.py
lookback/__main__.py
lookback/api.py
lookback/board.py
lookback/cli.py
lookback/configs.py
lookback/defaults.py
lookback/times.py
lookback-0.0.0.dist-info/entry_points.txt
lookback-0.0.0.dist-info/LICENSE
lookback-0.0.0.dist-info/WHEEL
lookback-0.0.0.dist-info/METADATA
lookback-0.0.0.dist-info/RECORD
