Metadata-Version: 2.1
Name: lookback
Version: 0.0.0
Summary: Utilities for analyzing Trello boards.
Author-email: Blake Naccarato <blake.naccarato+lookback@gmail.com>
Requires-Python: >=3.11
Requires-Dist: datamodel-code-generator~=0.16.0
Requires-Dist: pyperclip~=1.8.2
Requires-Dist: typer~=0.7.0
Project-URL: Home, https://github.com/blakeNaccarato/lookback
